odoo/addons/kpi_dashboard/README.rst
odoo/addons/kpi_dashboard/__init__.py
odoo/addons/kpi_dashboard/__manifest__.py
odoo/addons/kpi_dashboard/demo/demo_dashboard.xml
odoo/addons/kpi_dashboard/i18n/kpi_dashboard.pot
odoo/addons/kpi_dashboard/models/__init__.py
odoo/addons/kpi_dashboard/models/ir_actions_act_window_view.py
odoo/addons/kpi_dashboard/models/ir_ui_view.py
odoo/addons/kpi_dashboard/models/kpi_dashboard.py
odoo/addons/kpi_dashboard/models/kpi_kpi.py
odoo/addons/kpi_dashboard/readme/CONFIGURE.rst
odoo/addons/kpi_dashboard/readme/CONTRIBUTORS.rst
odoo/addons/kpi_dashboard/readme/DESCRIPTION.rst
odoo/addons/kpi_dashboard/security/ir.model.access.csv
odoo/addons/kpi_dashboard/security/security.xml
odoo/addons/kpi_dashboard/static/description/icon.png
odoo/addons/kpi_dashboard/static/description/index.html
odoo/addons/kpi_dashboard/static/lib/gauge/GaugeMeter.js
odoo/addons/kpi_dashboard/static/lib/gridster/jquery.dsmorse-gridster.min.css
odoo/addons/kpi_dashboard/static/lib/gridster/jquery.dsmorse-gridster.min.js
odoo/addons/kpi_dashboard/static/src/js/dashboard_controller.js
odoo/addons/kpi_dashboard/static/src/js/dashboard_model.js
odoo/addons/kpi_dashboard/static/src/js/dashboard_renderer.js
odoo/addons/kpi_dashboard/static/src/js/dashboard_view.js
odoo/addons/kpi_dashboard/static/src/js/field_widget.js
odoo/addons/kpi_dashboard/static/src/js/widget_registry.js
odoo/addons/kpi_dashboard/static/src/js/widget/abstract_widget.js
odoo/addons/kpi_dashboard/static/src/js/widget/counter_widget.js
odoo/addons/kpi_dashboard/static/src/js/widget/graph_widget.js
odoo/addons/kpi_dashboard/static/src/js/widget/integer_widget.js
odoo/addons/kpi_dashboard/static/src/js/widget/meter_widget.js
odoo/addons/kpi_dashboard/static/src/js/widget/number_widget.js
odoo/addons/kpi_dashboard/static/src/js/widget/text_widget.js
odoo/addons/kpi_dashboard/static/src/scss/kpi_dashboard.scss
odoo/addons/kpi_dashboard/static/src/xml/dashboard.xml
odoo12_addon_kpi_dashboard-12.0.1.3.0.dist-info/METADATA
odoo12_addon_kpi_dashboard-12.0.1.3.0.dist-info/WHEEL
odoo12_addon_kpi_dashboard-12.0.1.3.0.dist-info/top_level.txt
odoo12_addon_kpi_dashboard-12.0.1.3.0.dist-info/RECORD
