Metadata-Version: 2.1
Name: odoo12-addon-kpi-dashboard
Version: 12.0.1.3.0
Summary: Create Dashboards using kpis
Home-page: https://github.com/OCA/reporting-engine
Author: Creu Blanca,Odoo Community Association (OCA)
Author-email: support@odoo-community.org
License: AGPL-3
Platform: UNKNOWN
Classifier: Programming Language :: Python
Classifier: Framework :: Odoo
Classifier: License :: OSI Approved :: GNU Affero General Public License v3
Requires-Python: >=3.5
Requires-Dist: odoo12-addon-web-widget-color
Requires-Dist: odoo (<12.1dev,>=12.0a)
